README.txt
setup.cfg
setup.py
collective/__init__.py
collective.kssmessages.egg-info/PKG-INFO
collective.kssmessages.egg-info/SOURCES.txt
collective.kssmessages.egg-info/dependency_links.txt
collective.kssmessages.egg-info/entry_points.txt
collective.kssmessages.egg-info/namespace_packages.txt
collective.kssmessages.egg-info/not-zip-safe
collective.kssmessages.egg-info/requires.txt
collective.kssmessages.egg-info/top_level.txt
collective/kssmessages/__init__.py
collective/kssmessages/configure.zcml
collective/kssmessages/profiles.zcml
collective/kssmessages/browser/__init__.py
collective/kssmessages/browser/configure.zcml
collective/kssmessages/browser/kssmessages.css
collective/kssmessages/browser/kssmessages.js
collective/kssmessages/browser/plugin.js
collective/kssmessages/browser/popup.pt
collective/kssmessages/browser/popup.py
collective/kssmessages/browser/timeout_page.pt
collective/kssmessages/profiles/default/cssregistry.xml
collective/kssmessages/profiles/default/jsregistry.xml
docs/HISTORY.txt