Metadata-Version: 1.0
Name: collective.kssmessages
Version: 0.1
Summary: Show human-readable error messages when KSS timeouts or errors occur
Home-page: UNKNOWN
Author: Hedley Roos
Author-email: hedley@upfrontsystems.co.za
License: GPL
Platform: UNKNOWN
Classifier: Framework :: Plone
Classifier: Framework :: Zope2
Classifier: Programming Language :: Python
